setup.py
boggleboard/__init__.py
boggleboard/frequency.py
boggleboard/yawl.py
boggleboard.egg-info/PKG-INFO
boggleboard.egg-info/SOURCES.txt
boggleboard.egg-info/dependency_links.txt
boggleboard.egg-info/top_level.txt