Metadata-Version: 1.0
Name: boggleboard
Version: 1.0.4
Summary: Manipulate and analyse anagrams and variations of Boggle boards.
Home-page: http://www.site.uottawa.ca/~mraap046
Author: Sebastian Raaphorst
Author-email: srcoding@gmail.com
License: Apache 2.0
Keywords: boggle anagram anagrams board games puzzles
Platform: UNKNOWN
Classifier: License :: OSI Approved :: Apache Software License
Classifier: Programming Language :: Python
Classifier: Development Status :: 4 - Beta
Classifier: Intended Audience :: Developers
Classifier: Intended Audience :: Science/Research
Classifier: Intended Audience :: Education
Classifier: Topic :: Games/Entertainment :: Board Games
Classifier: Topic :: Games/Entertainment :: Puzzle Games
